MANIFEST.in
MetlogPsutils.spec
README.rst
setup.py
docs/Makefile
docs/source/conf.py
docs/source/config.rst
docs/source/index.rst
docs/source/msg_layout.rst
docs/source/api/psutil_plugin.rst
metlog_psutils/__init__.py
metlog_psutils/psutil_plugin.py
metlog_psutils.egg-info/PKG-INFO
metlog_psutils.egg-info/SOURCES.txt
metlog_psutils.egg-info/dependency_links.txt
metlog_psutils.egg-info/not-zip-safe
metlog_psutils.egg-info/requires.txt
metlog_psutils.egg-info/top_level.txt
metlog_psutils/tests/__init__.py
metlog_psutils/tests/cpuhog.py
metlog_psutils/tests/test_network.py
metlog_psutils/tests/test_psutils.py
metlog_psutils/tests/testbase.py