Metadata-Version: 1.0
Name: metlog-psutils
Version: 0.1
Summary: PSUtils extensions to metrics logging
Home-page: https://github.com/mozilla-services/metlog-psutils
Author: Victor Ng
Author-email: vng@mozilla.com
License: MPLv2.0
Keywords: metlog metrics logging client
Platform: UNKNOWN
Classifier: License :: OSI Approved :: Mozilla Public License 2.0 (MPL 2.0)
